{
  "bg": "https://www.siliconera.com/wp-content/uploads/2021/02/Genshin-Impact-Wallpapers-QiQi-Venti-01.jpg",
  "bg03": "https://wallpapercave.com/wp/wp7486978.jpg",
  "bg02": "https://wallpapercave.com/wp/wp7487029.jpg",
  "title": "#Genshin Impact",
  "description": "Um quiz rápido sobre Genshin Impact!!!",
  "questions": [
    {
      "image": "https://media3.giphy.com/media/iFmw13LV1hHhViPPWz/source.gif",
      "title": "O que é React?",
      "description": "Pergunta fácil em!",
      "answer": 0,
      "alternatives": [
        "Biblioteca",
        "Ferramenta",
        "Framework",
        "Linguagem"
      ]
    },
    {
      "image": "https://i.pinimg.com/originals/f1/06/68/f106688b20ed32598e454b91cb2db3fe.gif",
      "title": "ReactJS e React Native são a mesma coisa?",
      "description": "E agora? Você sabe?",
      "answer": 1,
      "alternatives": [
        "Sim",
        "Não"
      ]
    },
    {
      "image": "https://cdn.dicionariopopular.com/imagens/giphy-1.gif",
      "title": "React Native trabalha em que ambiente?",
      "answer": 1,
      "alternatives": [
        "Web (Browser)",
        "Mobile (Smartphone)",
        "Web (Browser) e Mobile (Smartphone)",
        "Automação"
      ]
    },
    {
      "image": "https://i.pinimg.com/originals/11/df/58/11df58e8d717e9358c502a66156ed374.gif",
      "title": "ReactJS trabalha em que ambiente?",
      "answer": 0,
      "alternatives": [
        "Web (Browser)",
        "Mobile (Smartphone)",
        "Web (Browser) e Mobile (Smartphone)",
        "Automação"
      ]
    },
    {
      "image": "http://www.riclan.com.br/wp-content/uploads/2017/12/tenor.gif",
      "title": "Qual a proposta de React?",
      "answer": 2,
      "alternatives": [
        "SPA(Sinple Position Away)",
        "SPA(Single Patern App)",
        "SPA(Single Page Aplication)",
        "SPA(SOAP Patern Aplication)"
      ]
    },
    {
      "image": "https://steamuserimages-a.akamaihd.net/ugc/909045930377493237/BEB26F0DEC34EF4F06205E5C923FC278D2FBE220/",
      "title": "O React trabalha com ?",
      "answer": 0,
      "alternatives": [
        "Componentização de elementos",
        "Renderização de paginas inteiras",
        "Somente desenvolvimento mobile",
        "Somente desenvolvimento web"
      ]
    },
    {
      "image": "https://www.humordido.net/wp-content/uploads/2018/08/ue-meme.gif",
      "title": "Quais os estagios da vida util de um componente?",
      "answer": 3,
      "alternatives": [
        "Inicialização , Inserção de Dados e Destruição",
        "Inicialização , Atualizações de Estados e Renderização",
        "Inicialização , Renderização e Destruição",
        "Inicialização , Atualizações de Estados e Destruição"
      ]
    },
    {
      "image": "https://img.ibxk.com.br/2020/07/08/08183627871446.gif",
      "title": "A Sintaxe utilizada no desenvolvimento em React é?",
      "answer": 1,
      "alternatives": [
        "JSX(JSON XML)",
        "JSX(JavaScrip XML)",
        "JSX(Java XML)",
        "JSX(Jam XML)"
      ]
    },
    {
      "image": "https://1.bp.blogspot.com/-v5CUkH3ziOE/XY0hKdhN-oI/AAAAAAAACAk/kwdl2E86v5EBK1G4o8_TkhNBGYWuKxpJgCEwYBhgL/s1600/tombou.gif",
      "title": "Que recurso usamos para controlar as rotas das paginas?",
      "answer": 0,
      "alternatives": [
        "react router",
        "javascrit router",
        "router page",
        "router fetch"
      ]
    },
    {
      "image": "https://thumbs.gfycat.com/WaterySarcasticCollardlizard-size_restricted.gif",
      "title": "Para que server o Redux?",
      "description": "Essa é pra fecha!!!",
      "answer": 3,
      "alternatives": [
        "Serve para auxiliar o desenvolvedor na sintaxe JSX",
        "Serve para renderizar paginas do react",
        "Serve para inserir dados no banco de dados",
        "Serve para o armazenamento de estados de aplicações JavaScript"
      ]
    }
  ],
  "result01":{
    "image": "https://i.pinimg.com/originals/7f/87/85/7f87859ef3e53862b0ab165877bd29b3.gif",
    "description": "Desonra pra tu desonra pra tua vaca!"
  },
  "result02":{
    "image": "https://media1.tenor.com/images/e20499538f2334e250cd85d8803119b1/tenor.gif?itemid=4803574",
    "description": "Parabens esta aprendendo, continue assim!!!"
  },
  "result03":{
    "image": "https://i.pinimg.com/originals/58/43/53/584353bb2917b5f7793546331f73f9df.gif",
    "description": "Show tu manja bastante de React!"
  },
  "result04":{
    "image": "http://media.tumblr.com/d94c1acc13d31bd34028eeb7df39ba39/tumblr_inline_momfyuUOMB1qz4rgp.gif",
    "description": "HHHHHOOOOOOOOOO TU É UM MONSTRO EM REACT PARABENS!!!"
  },
  "external": [
    "https://strangerquiz.felipeoes.vercel.app/",
    "https://flash-quiz-next.davidlpc1.vercel.app/",
    "https://doctor-who-quiz.emanuelpna.vercel.app/",
    "https://brunoquiz.brunosaibert.vercel.app/",
    "https://harry-potter-quiz.lucianoweslen11.vercel.app",
    "https://lotr-quiz.filipe1309.vercel.app/",
    "https://quiz-cavaleiro-zodiaco.vercel.app/",
    "https://quiz-games.gabrielwolf-dev.vercel.app/",
    "https://aluraquiz-base.renatofrancisco.vercel.app/",
    "https://alura-quiz-ferro-e-fogo.fpzero.vercel.app/",
    "https://imersao-react-next-alura.samuel-mota.vercel.app/",
    "https://aluraquiz-coffee.leonardot07.vercel.app/",
    "https://aluraquiz-halloween.lucaskuhn.vercel.app/",
    "https://you-dont-know-js-quiz.zlincon.vercel.app/",
    "https://aluraquiz-css.omariosouto.vercel.app/",
    "https://aluraquiz-devsoutinho.omariosouto.vercel.app/"
  ],
  "theme": {
    "colors": {
      "primary": "#222222",
      "secondary": "#A284DF",
      "github": "#2dcfff",
      "mainBg": "#3D2AA8",
      "contrastText": "#FFFFFF",
      "wrong": "#FF5722",
      "success": "#4CAF50"
    },
    "borderRadius": "4px"
  }
}
